wasd2play/__init__.py
wasd2play/run.py
wasd2play/wasd_lib.py
wasd2play-0.4.6.dist-info/LICENSE.md
wasd2play-0.4.6.dist-info/METADATA
wasd2play-0.4.6.dist-info/WHEEL
wasd2play-0.4.6.dist-info/entry_points.txt
wasd2play-0.4.6.dist-info/top_level.txt
wasd2play-0.4.6.dist-info/RECORD
