Metadata-Version: 2.1
Name: wasd2play
Version: 0.4.6
Summary: Open wasd.tv streams in your favorite player!
Home-page: https://github.com/viktor02/wasd2play
Author: Viktor Karpov
Author-email: v@vitka-k.ru
License: MIT
Platform: UNKNOWN
Classifier: Programming Language :: Python :: 3
Classifier: License :: OSI Approved :: MIT License
Classifier: Operating System :: OS Independent
Requires-Dist: requests (>=2.24.0)
